pycrop/__init__.py
pycrop/tools.py
pycrop-1.0.1.dist-info/METADATA
pycrop-1.0.1.dist-info/WHEEL
pycrop-1.0.1.dist-info/top_level.txt
pycrop-1.0.1.dist-info/RECORD
