Metadata-Version: 2.1
Name: pycrop
Version: 1.0.1
Summary: Methods to manipulate images
Home-page: https://github.com/giorgi94/pycrop
Author: Giorgi Kakulashvili
Author-email: UNKNOWN
License: MIT
Keywords: pillow,contain,cover
Platform: OS Independent
Requires-Dist: Pillow (>=5.3.0)
